nassl/__init__.py
nassl/_nassl.cpython-314-x86_64-linux-musl.so
nassl/_nassl.pyi
nassl/_nassl_legacy.cpython-314-x86_64-linux-musl.so
nassl/_nassl_legacy.pyi
nassl/cert_chain_verifier.py
nassl/ephemeral_key_info.py
nassl/legacy_ssl_client.py
nassl/ocsp_response.py
nassl/py.typed
nassl/ssl_client.py
tests/openssl_server/__init__.py
nassl-5.4.0.dist-info/METADATA
nassl-5.4.0.dist-info/WHEEL
nassl-5.4.0.dist-info/top_level.txt
nassl-5.4.0.dist-info/RECORD
nassl-5.4.0.dist-info/licenses/LICENSE.txt
